ogeth/__init__.py
ogeth/calibrate.py
ogeth/constants.py
ogeth/income.py
ogeth/input_output.py
ogeth/labor.py
ogeth/macro_params.py
ogeth/ogeth_default_parameters.json
ogeth/test_est_chi_n.py
ogeth/utils.py
ogeth/data/IFPRI_SAM_ETH_2022_SAM.csv
ogeth-0.0.5.dist-info/licenses/LICENSE
ogeth-0.0.5.dist-info/METADATA
ogeth-0.0.5.dist-info/WHEEL
ogeth-0.0.5.dist-info/top_level.txt
ogeth-0.0.5.dist-info/RECORD
